clvm/BaseSExp.py
clvm/EvalError.py
clvm/SExp.py
clvm/__init__.py
clvm/casts.py
clvm/core_ops.py
clvm/costs.py
clvm/more_ops.py
clvm/op_utils.py
clvm/operators.py
clvm/run_program.py
clvm/serialize.py
clvm/version.py
clvm/ecdsa/Curve.py
clvm/ecdsa/Generator.py
clvm/ecdsa/Point.py
clvm/ecdsa/__init__.py
clvm/ecdsa/bls12_381.py
clvm/ecdsa/intstream.py
clvm-0.41.dist-info/LICENSE
clvm-0.41.dist-info/METADATA
clvm-0.41.dist-info/WHEEL
clvm-0.41.dist-info/top_level.txt
clvm-0.41.dist-info/RECORD
